spin/__init__.py
spin_cli-0.0.0.dist-info/METADATA
spin_cli-0.0.0.dist-info/WHEEL
spin_cli-0.0.0.dist-info/top_level.txt
spin_cli-0.0.0.dist-info/RECORD
