Metadata-Version: 2.1
Name: spin-cli
Version: 0.0.0
Summary: Package description here.
Home-page: UNKNOWN
Author: Niklas Rosenstein
Author-email: rosensteinniklas@gmail.com
License: UNKNOWN
Platform: UNKNOWN
